Metadata-Version: 1.1
Name: mcldashauthfb
Version: 0.0.1
Summary: facebook authentication for dash
Home-page: UNKNOWN
Author: marco vargas <monitorcasalab@gmail.com>
Author-email: UNKNOWN
License: MIT
Platform: UNKNOWN
Classifier: Framework :: Dash
